sciop_scraping-0.3.1.dist-info/METADATA
sciop_scraping-0.3.1.dist-info/WHEEL
sciop_scraping-0.3.1.dist-info/entry_points.txt
sciop_scraping-0.3.1.dist-info/licenses/LICENSE
sciop_scraping/__init__.py
sciop_scraping/cli/__init__.py
sciop_scraping/cli/api.py
sciop_scraping/cli/common.py
sciop_scraping/cli/main.py
sciop_scraping/cli/state.py
sciop_scraping/const.py
sciop_scraping/exceptions.py
sciop_scraping/middlewares.py
sciop_scraping/mixins/__init__.py
sciop_scraping/mixins/filter.py
sciop_scraping/mixins/s3.py
sciop_scraping/mixins/wayback.py
sciop_scraping/pipelines.py
sciop_scraping/quests/__init__.py
sciop_scraping/quests/base.py
sciop_scraping/quests/chronicling/__init__.py
sciop_scraping/quests/chronicling/cli.py
sciop_scraping/quests/chronicling/quest.py
sciop_scraping/quests/chronicling/spider.py
sciop_scraping/quests/poes/__init__.py
sciop_scraping/quests/poes/cli.py
sciop_scraping/quests/poes/spider.py
sciop_scraping/quests/smithsonian/__init__.py
sciop_scraping/quests/smithsonian/cli.py
sciop_scraping/quests/smithsonian/const.py
sciop_scraping/quests/smithsonian/quest.py
sciop_scraping/quests/smithsonian/spider.py
sciop_scraping/quests/us_oig/__init__.py
sciop_scraping/quests/us_oig/cli.py
sciop_scraping/quests/us_oig/spider.py
sciop_scraping/settings.py
sciop_scraping/validation.py
sciop_scraping-0.3.1.dist-info/RECORD
