Metadata-Version: 2.1
Name: sciop-scraping
Version: 0.3.1
Summary: scraping code to use with sciop-coordinated scrapes
Author-Email: sneakers-the-rat <sneakers-the-rat@protonmail.com>
License: EUPL-1.2
Project-URL: repository, https://codeberg.org/safeguarding/sciop-scraping
Project-URL: homepage, https://codeberg.org/safeguarding/sciop-scraping
Requires-Python: >=3.11
Requires-Dist: sciop-cli>=0.2.0
Requires-Dist: click>=8.2.1
Requires-Dist: scrapy>=2.13.0
Requires-Dist: tqdm>=4.67.1
Provides-Extra: test
Requires-Dist: pytest>=8.3.5; extra == "test"
Requires-Dist: bagit>=1.9.0; extra == "test"
Provides-Extra: dev
Requires-Dist: black>=25.1.0; extra == "dev"
Requires-Dist: ruff>=0.12.4; extra == "dev"
